[
    {
        "code":"MA1486",
        "name":"Matematisk probleml\u00f6sning",
        "points":4.0,
        "semester":"H\u00f6sttermin 2022",
        "start_week":202234,
        "end_week":202243,
        "period":1,
        "type":"Obligatorisk",
        "focus":null,
        "prerequisites":"Grundl\u00e4ggande beh\u00f6righet samt Matematik 4 och Fysik 2.",
        "teacher":"lmt",
        "teacher_url":"https:\/\/www.bth.se\/?searchtype=employee&s=lmt",
        "replacement":null,
        "next_instance":null,
        "syllabus_url":"https:\/\/edu.bth.se\/utbildning\/redirect.asp?KtAnmKod=BXHYQ&KtTermin=20222&lang=sv",
        "education_plan_url":"https:\/\/edu.bth.se\/utbildningsplaner\/IEACI_HT-22.pdf"
    },
    {
        "code":"TE1421",
        "name":"Teknisk introduktionskurs med ingenj\u00f6rsmetodik",
        "points":8.0,
        "semester":"H\u00f6sttermin 2022",
        "start_week":202235,
        "end_week":202302,
        "period":1,
        "type":"Obligatorisk",
        "focus":null,
        "prerequisites":"Grundl\u00e4ggande beh\u00f6righet + Fysik 2, Kemi 1, Matematik 4. Eller: Fysik B, Kemi A, Matematik E.",
        "teacher":"gkn",
        "teacher_url":"https:\/\/www.bth.se\/?searchtype=employee&s=gkn",
        "replacement":null,
        "next_instance":null,
        "syllabus_url":"https:\/\/edu.bth.se\/utbildning\/redirect.asp?KtAnmKod=BFMQG&KtTermin=20222&lang=sv",
        "education_plan_url":"https:\/\/edu.bth.se\/utbildningsplaner\/IEACI_HT-22.pdf"
    },
    {
        "code":"IY1418",
        "name":"Grunderna i industriell ekonomi",
        "points":6.0,
        "semester":"H\u00f6sttermin 2022",
        "start_week":202235,
        "end_week":202243,
        "period":1,
        "type":"Obligatorisk",
        "focus":null,
        "prerequisites":"Grundl\u00e4ggande beh\u00f6righet.",
        "teacher":null,
        "teacher_url":null,
        "replacement":null,
        "next_instance":"202436 (BXRUQ)",
        "syllabus_url":"https:\/\/edu.bth.se\/utbildning\/redirect.asp?KtAnmKod=BULXU&KtTermin=20222&lang=sv",
        "education_plan_url":"https:\/\/edu.bth.se\/utbildningsplaner\/IEACI_HT-22.pdf"
    },
    {
        "code":"MA1448",
        "name":"Linj\u00e4r algebra 1",
        "points":6.0,
        "semester":"H\u00f6sttermin 2022",
        "start_week":202244,
        "end_week":202302,
        "period":2,
        "type":"Obligatorisk",
        "focus":null,
        "prerequisites":"Grundl\u00e4ggande beh\u00f6righet samt Matematik 4 och Fysik 2.",
        "teacher":"stw",
        "teacher_url":"https:\/\/www.bth.se\/?searchtype=employee&s=stw",
        "replacement":"MA1498",
        "next_instance":"202436 (G5954)",
        "syllabus_url":"https:\/\/edu.bth.se\/utbildning\/redirect.asp?KtAnmKod=BEPPH&KtTermin=20222&lang=sv",
        "education_plan_url":"https:\/\/edu.bth.se\/utbildningsplaner\/IEACI_HT-22.pdf"
    },
    {
        "code":"IY1417",
        "name":"Till\u00e4mpad mikroekonomi och strategi",
        "points":6.0,
        "semester":"H\u00f6sttermin 2022",
        "start_week":202244,
        "end_week":202302,
        "period":2,
        "type":"Obligatorisk",
        "focus":null,
        "prerequisites":"Grundl\u00e4ggande beh\u00f6righet.",
        "teacher":null,
        "teacher_url":null,
        "replacement":null,
        "next_instance":null,
        "syllabus_url":"https:\/\/edu.bth.se\/utbildning\/redirect.asp?KtAnmKod=BJYAL&KtTermin=20222&lang=sv",
        "education_plan_url":"https:\/\/edu.bth.se\/utbildningsplaner\/IEACI_HT-22.pdf"
    },
    {
        "code":"FY1431",
        "name":"Fysik grundkurs",
        "points":6.0,
        "semester":"V\u00e5rtermin 2023",
        "start_week":202303,
        "end_week":202312,
        "period":3,
        "type":"Obligatorisk",
        "focus":null,
        "prerequisites":"Grundl\u00e4ggande beh\u00f6righet samt Matematik 3c och Fysik 2.",
        "teacher":"pgr",
        "teacher_url":"https:\/\/www.bth.se\/?searchtype=employee&s=pgr",
        "replacement":"FY1435",
        "next_instance":"202436 (BRE4W)",
        "syllabus_url":"https:\/\/edu.bth.se\/utbildning\/redirect.asp?KtAnmKod=BWFX7&KtTermin=20231&lang=sv",
        "education_plan_url":"https:\/\/edu.bth.se\/utbildningsplaner\/IEACI_HT-22.pdf"
    },
    {
        "code":"MA1444",
        "name":"Analys 1",
        "points":6.0,
        "semester":"V\u00e5rtermin 2023",
        "start_week":202303,
        "end_week":202312,
        "period":3,
        "type":"Obligatorisk",
        "focus":null,
        "prerequisites":"Omr\u00e5desbeh\u00f6righet 9: Matematik E, Fysik B. (Kemi A kr\u00e4vs ej)  eller omr\u00e5desbeh\u00f6righet A9: Matematik 4, Fysik 2. (Kemi 1 kr\u00e4vs ej).",
        "teacher":"stw",
        "teacher_url":"https:\/\/www.bth.se\/?searchtype=employee&s=stw",
        "replacement":"MA1499",
        "next_instance":"202445 (BFKCN)",
        "syllabus_url":"https:\/\/edu.bth.se\/utbildning\/redirect.asp?KtAnmKod=BP7QF&KtTermin=20231&lang=sv",
        "education_plan_url":"https:\/\/edu.bth.se\/utbildningsplaner\/IEACI_HT-22.pdf"
    },
    {
        "code":"DV1574",
        "name":"Programmering och probleml\u00f6sning med Python",
        "points":6.0,
        "semester":"V\u00e5rtermin 2023",
        "start_week":202303,
        "end_week":202312,
        "period":3,
        "type":"Obligatorisk",
        "focus":null,
        "prerequisites":"Grundl\u00e4ggande beh\u00f6righet",
        "teacher":null,
        "teacher_url":null,
        "replacement":null,
        "next_instance":"202445 (BN4J7)",
        "syllabus_url":"https:\/\/edu.bth.se\/utbildning\/redirect.asp?KtAnmKod=BNWPY&KtTermin=20231&lang=sv",
        "education_plan_url":"https:\/\/edu.bth.se\/utbildningsplaner\/IEACI_HT-22.pdf"
    },
    {
        "code":"MA1494",
        "name":"Analys 2",
        "points":6.0,
        "semester":"V\u00e5rtermin 2023",
        "start_week":202313,
        "end_week":202322,
        "period":4,
        "type":"Obligatorisk",
        "focus":null,
        "prerequisites":"F\u00f6r tilltr\u00e4de till kursen kr\u00e4vs genomg\u00e5ngen kurs Analys 1, 6 hp.",
        "teacher":"aas",
        "teacher_url":"https:\/\/www.bth.se\/?searchtype=employee&s=aas",
        "replacement":"MA1500",
        "next_instance":"202504 (BUD44)",
        "syllabus_url":"https:\/\/edu.bth.se\/utbildning\/redirect.asp?KtAnmKod=BKYDH&KtTermin=20231&lang=sv",
        "education_plan_url":"https:\/\/edu.bth.se\/utbildningsplaner\/IEACI_HT-22.pdf"
    },
    {
        "code":"IY1439",
        "name":"F\u00f6retag och organisation",
        "points":6.0,
        "semester":"V\u00e5rtermin 2023",
        "start_week":202313,
        "end_week":202322,
        "period":4,
        "type":"Obligatorisk",
        "focus":null,
        "prerequisites":"Grundl\u00e4ggande beh\u00f6righet.",
        "teacher":null,
        "teacher_url":null,
        "replacement":null,
        "next_instance":null,
        "syllabus_url":"https:\/\/edu.bth.se\/utbildning\/redirect.asp?KtAnmKod=BAUJX&KtTermin=20231&lang=sv",
        "education_plan_url":"https:\/\/edu.bth.se\/utbildningsplaner\/IEACI_HT-22.pdf"
    },
    {
        "code":"SL1418",
        "name":"Grundkurs i h\u00e5llbar utveckling",
        "points":6.0,
        "semester":"H\u00f6sttermin 2023",
        "start_week":202335,
        "end_week":202402,
        "period":1,
        "type":"Obligatorisk",
        "focus":null,
        "prerequisites":"Grundl\u00e4ggande beh\u00f6righet",
        "teacher":"ctt",
        "teacher_url":"https:\/\/www.bth.se\/?searchtype=employee&s=ctt",
        "replacement":"SL1421",
        "next_instance":null,
        "syllabus_url":"https:\/\/edu.bth.se\/utbildning\/redirect.asp?KtAnmKod=BKHHF&KtTermin=20232&lang=sv",
        "education_plan_url":"https:\/\/edu.bth.se\/utbildningsplaner\/IEACI_HT-22.pdf"
    },
    {
        "code":"MA1446",
        "name":"Diskret matematik",
        "points":6.0,
        "semester":"H\u00f6sttermin 2023",
        "start_week":202335,
        "end_week":202343,
        "period":1,
        "type":"Obligatorisk",
        "focus":null,
        "prerequisites":"Genomg\u00e5ngna kurser Matematik, grundkurs, 4 hp alternativt Matematisk probleml\u00f6sning, 4 hp och Linj\u00e4r algebra 1, 6 hp eller motsvarande.",
        "teacher":"jch",
        "teacher_url":"https:\/\/www.bth.se\/?searchtype=employee&s=jch",
        "replacement":"MA1504",
        "next_instance":"202514 (BHK34)",
        "syllabus_url":"https:\/\/edu.bth.se\/utbildning\/redirect.asp?KtAnmKod=BU37X&KtTermin=20232&lang=sv",
        "education_plan_url":"https:\/\/edu.bth.se\/utbildningsplaner\/IEACI_HT-22.pdf"
    },
    {
        "code":"IY1421",
        "name":"F\u00f6retaget i en global ekonomi",
        "points":6.0,
        "semester":"H\u00f6sttermin 2023",
        "start_week":202335,
        "end_week":202343,
        "period":1,
        "type":"Obligatorisk",
        "focus":null,
        "prerequisites":"Grundl\u00e4ggande beh\u00f6righet samt genomg\u00e5ngna kurser i Till\u00e4mpad mikroekonomi och strategi 6 hp och F\u00f6retag och organisation 6 hp.",
        "teacher":"ebr",
        "teacher_url":"https:\/\/www.bth.se\/?searchtype=employee&s=ebr",
        "replacement":null,
        "next_instance":"202436 (BFLLH)",
        "syllabus_url":"https:\/\/edu.bth.se\/utbildning\/redirect.asp?KtAnmKod=BRUKJ&KtTermin=20232&lang=sv",
        "education_plan_url":"https:\/\/edu.bth.se\/utbildningsplaner\/IEACI_HT-22.pdf"
    },
    {
        "code":"MA1447",
        "name":"Flervariabelanalys",
        "points":6.0,
        "semester":"H\u00f6sttermin 2023",
        "start_week":202344,
        "end_week":202402,
        "period":2,
        "type":"Obligatorisk",
        "focus":null,
        "prerequisites":"F\u00f6r tilltr\u00e4de till kursen kr\u00e4vs genomg\u00e5ngna kurser Linj\u00e4r algebra 6 hp, Analys 6 hp och Analys 2 6 hp.",
        "teacher":"jch",
        "teacher_url":"https:\/\/www.bth.se\/?searchtype=employee&s=jch",
        "replacement":null,
        "next_instance":"202445 (BHDQR)",
        "syllabus_url":"https:\/\/edu.bth.se\/utbildning\/redirect.asp?KtAnmKod=BTEQR&KtTermin=20232&lang=sv",
        "education_plan_url":"https:\/\/edu.bth.se\/utbildningsplaner\/IEACI_HT-22.pdf"
    },
    {
        "code":"FY1423",
        "name":"Fysik f\u00f6r ingenj\u00f6rer 2",
        "points":6.0,
        "semester":"H\u00f6sttermin 2023",
        "start_week":202344,
        "end_week":202402,
        "period":2,
        "type":"Obligatorisk",
        "focus":null,
        "prerequisites":"Avklarade kurser: Analys 1 (MA1444), Fysik Grundkurs (FY1422). Genomg\u00e5ngen kurs: Analys 2 (MA1445).",
        "teacher":"meo",
        "teacher_url":"https:\/\/www.bth.se\/?searchtype=employee&s=meo",
        "replacement":null,
        "next_instance":"202445 (BG4A9)",
        "syllabus_url":"https:\/\/edu.bth.se\/utbildning\/redirect.asp?KtAnmKod=BHA4M&KtTermin=20232&lang=sv",
        "education_plan_url":"https:\/\/edu.bth.se\/utbildningsplaner\/IEACI_HT-22.pdf"
    },
    {
        "code":"FY1424",
        "name":"Fysik f\u00f6r ingenj\u00f6rer 3",
        "points":6.0,
        "semester":"V\u00e5rtermin 2024",
        "start_week":202403,
        "end_week":202412,
        "period":3,
        "type":"Obligatorisk",
        "focus":null,
        "prerequisites":"F\u00f6r tilltr\u00e4de till kursen kr\u00e4vs avklarade kurser Analys 2, 6 hp och Fysik f\u00f6r ingenj\u00f6rer 1, 4 hp, samt genomg\u00e5ngen kurs Fysik f\u00f6r ingenj\u00f6rer 2, 6 hp.",
        "teacher":"meo",
        "teacher_url":"https:\/\/www.bth.se\/?searchtype=employee&s=meo",
        "replacement":null,
        "next_instance":"202504 (BY3DF)",
        "syllabus_url":"https:\/\/edu.bth.se\/utbildning\/redirect.asp?KtAnmKod=BQ9XM&KtTermin=20241&lang=sv",
        "education_plan_url":"https:\/\/edu.bth.se\/utbildningsplaner\/IEACI_HT-22.pdf"
    },
    {
        "code":"IY1419",
        "name":"Industriell marknadsf\u00f6ring - teori och praktik",
        "points":6.0,
        "semester":"V\u00e5rtermin 2024",
        "start_week":202403,
        "end_week":202412,
        "period":3,
        "type":"Obligatorisk",
        "focus":null,
        "prerequisites":"Grundl\u00e4ggande beh\u00f6righet samt genomg\u00e5ngen kurs i Mikroekonomi och strategi 6 hp.",
        "teacher":"vji",
        "teacher_url":"https:\/\/www.bth.se\/?searchtype=employee&s=vji",
        "replacement":null,
        "next_instance":"202504 (BN7FX)",
        "syllabus_url":"https:\/\/edu.bth.se\/utbildning\/redirect.asp?KtAnmKod=B3FFR&KtTermin=20241&lang=sv",
        "education_plan_url":"https:\/\/edu.bth.se\/utbildningsplaner\/IEACI_HT-22.pdf"
    },
    {
        "code":"PA1473",
        "name":"Programvaruutveckling",
        "points":6.0,
        "semester":"V\u00e5rtermin 2024",
        "start_week":202403,
        "end_week":202422,
        "period":3,
        "type":"Obligatorisk",
        "focus":null,
        "prerequisites":"F\u00f6r tilltr\u00e4de till kursen kr\u00e4vs genomg\u00e5ngna 8 hp inom introduktion till ingenj\u00f6rsmetodik och genomg\u00e5ngna 6 hp inom programmering.",
        "teacher":"jgh",
        "teacher_url":"https:\/\/www.bth.se\/?searchtype=employee&s=jgh",
        "replacement":"PA1484",
        "next_instance":"202504 (B9MJU)",
        "syllabus_url":"https:\/\/edu.bth.se\/utbildning\/redirect.asp?KtAnmKod=BJGLG&KtTermin=20241&lang=sv",
        "education_plan_url":"https:\/\/edu.bth.se\/utbildningsplaner\/IEACI_HT-22.pdf"
    },
    {
        "code":"DV1664",
        "name":"Introduktion till databaser",
        "points":6.0,
        "semester":"V\u00e5rtermin 2024",
        "start_week":202413,
        "end_week":202422,
        "period":4,
        "type":"Obligatorisk",
        "focus":null,
        "prerequisites":"F\u00f6r tilltr\u00e4de till kursen kr\u00e4vs att studenten har avklarat 6 hp i programmering.",
        "teacher":"abc",
        "teacher_url":"https:\/\/www.bth.se\/?searchtype=employee&s=abc",
        "replacement":null,
        "next_instance":"202514 (B6LAK)",
        "syllabus_url":"https:\/\/edu.bth.se\/utbildning\/redirect.asp?KtAnmKod=BW9NM&KtTermin=20241&lang=sv",
        "education_plan_url":"https:\/\/edu.bth.se\/utbildningsplaner\/IEACI_HT-22.pdf"
    },
    {
        "code":"MT1463",
        "name":"Datorst\u00f6d f\u00f6r ingenj\u00f6rsarbete",
        "points":6.0,
        "semester":"V\u00e5rtermin 2024",
        "start_week":202413,
        "end_week":202422,
        "period":4,
        "type":"Obligatorisk",
        "focus":null,
        "prerequisites":"Grundl\u00e4ggande beh\u00f6righet",
        "teacher":"mzw",
        "teacher_url":"https:\/\/www.bth.se\/?searchtype=employee&s=mzw",
        "replacement":null,
        "next_instance":"202514 (BYLKN)",
        "syllabus_url":"https:\/\/edu.bth.se\/utbildning\/redirect.asp?KtAnmKod=BLDJ4&KtTermin=20241&lang=sv",
        "education_plan_url":"https:\/\/edu.bth.se\/utbildningsplaner\/IEACI_HT-22.pdf"
    },
    {
        "code":"MT1506",
        "name":"H\u00e5llfasthetsl\u00e4ra grundkurs",
        "points":6.0,
        "semester":"H\u00f6sttermin 2024",
        "start_week":202436,
        "end_week":202444,
        "period":1,
        "type":"Obligatorisk",
        "focus":"Maskinteknik och h\u00e5llbar produktinnovation",
        "prerequisites":"F\u00f6r tilltr\u00e4de till kursen kr\u00e4vs att 1,5 hp fr\u00e5n kursen Fysik grundkurs samt 1,5 hp fr\u00e5n kursen Analys 1 \u00e4r avklarade.",
        "teacher":"mdm",
        "teacher_url":"https:\/\/www.bth.se\/?searchtype=employee&s=mdm",
        "replacement":null,
        "next_instance":"202436 (BFPEU)",
        "syllabus_url":"https:\/\/edu.bth.se\/utbildning\/redirect.asp?KtAnmKod=BFPEU&KtTermin=20242&lang=sv",
        "education_plan_url":"https:\/\/edu.bth.se\/utbildningsplaner\/IEACI_HT-22.pdf"
    },
    {
        "code":"MS1405",
        "name":"Matematisk statistik",
        "points":6.0,
        "semester":"H\u00f6sttermin 2024",
        "start_week":202436,
        "end_week":202444,
        "period":1,
        "type":"Obligatorisk",
        "focus":"Maskinteknik och h\u00e5llbar produktinnovation",
        "prerequisites":"Genomg\u00e5ngna kurser i Analys 12 hp samt Linj\u00e4r algebra 6 hp (eller motsvarande).\n",
        "teacher":"bxp",
        "teacher_url":"https:\/\/www.bth.se\/?searchtype=employee&s=bxp",
        "replacement":null,
        "next_instance":"202436 (BFMLU)",
        "syllabus_url":"https:\/\/bth.azure-api.net\/lindplan\/courseplanbycode?code=BFMLU&semester=20242&lang=sv",
        "education_plan_url":"https:\/\/edu.bth.se\/utbildningsplaner\/IEACI_HT-22.pdf"
    },
    {
        "code":"MS1405",
        "name":"Matematisk statistik",
        "points":6.0,
        "semester":"H\u00f6sttermin 2024",
        "start_week":202436,
        "end_week":202444,
        "period":1,
        "type":"Obligatorisk",
        "focus":"Industriell mjukvaruutveckling",
        "prerequisites":"Genomg\u00e5ngna kurser i Analys 12 hp samt Linj\u00e4r algebra 6 hp (eller motsvarande).\n",
        "teacher":"bxp",
        "teacher_url":"https:\/\/www.bth.se\/?searchtype=employee&s=bxp",
        "replacement":null,
        "next_instance":"202436 (BFMLU)",
        "syllabus_url":"https:\/\/bth.azure-api.net\/lindplan\/courseplanbycode?code=BFMLU&semester=20242&lang=sv",
        "education_plan_url":"https:\/\/edu.bth.se\/utbildningsplaner\/IEACI_HT-22.pdf"
    },
    {
        "code":"DV1582",
        "name":"Programmering i Python, forts\u00e4ttningskurs",
        "points":6.0,
        "semester":"H\u00f6sttermin 2024",
        "start_week":202436,
        "end_week":202444,
        "period":1,
        "type":"Obligatorisk",
        "focus":"Industriell mjukvaruutveckling",
        "prerequisites":"F\u00f6r tilltr\u00e4de till kursen kr\u00e4vs genomg\u00e5ngen kurs, Programmering och probleml\u00f6sning med Python, 6 hp, varav minst 2 hp ska vara avklarade.",
        "teacher":"pej",
        "teacher_url":"https:\/\/www.bth.se\/?searchtype=employee&s=pej",
        "replacement":null,
        "next_instance":"202436 (BW3MG)",
        "syllabus_url":"https:\/\/edu.bth.se\/utbildning\/redirect.asp?KtAnmKod=BW3MG&KtTermin=20242&lang=sv",
        "education_plan_url":"https:\/\/edu.bth.se\/utbildningsplaner\/IEACI_HT-22.pdf"
    },
    {
        "code":"MT1556",
        "name":"Innovativ och h\u00e5llbar produktutveckling 1",
        "points":6.0,
        "semester":"H\u00f6sttermin 2024",
        "start_week":202436,
        "end_week":202444,
        "period":1,
        "type":"Obligatorisk",
        "focus":"Maskinteknik och h\u00e5llbar produktinnovation",
        "prerequisites":"F\u00f6r tilltr\u00e4de till kursen kr\u00e4vs 75 avklarade h\u00f6gskolepo\u00e4ng fr\u00e5n ett ingenj\u00f6rsprogram inom maskinteknik eller industriell ekonomi inkluderande avklarad kurs H\u00e5llbarhetsgrunder, 6 hp.",
        "teacher":"ber",
        "teacher_url":"https:\/\/www.bth.se\/?searchtype=employee&s=ber",
        "replacement":null,
        "next_instance":"202436 (BRKHY)",
        "syllabus_url":"https:\/\/edu.bth.se\/utbildning\/redirect.asp?KtAnmKod=BRKHY&KtTermin=20242&lang=sv",
        "education_plan_url":"https:\/\/edu.bth.se\/utbildningsplaner\/IEACI_HT-22.pdf"
    },
    {
        "code":"MT1556",
        "name":"Innovativ och h\u00e5llbar produktutveckling 1",
        "points":6.0,
        "semester":"H\u00f6sttermin 2024",
        "start_week":202436,
        "end_week":202444,
        "period":1,
        "type":"Obligatorisk",
        "focus":"Industriell mjukvaruutveckling",
        "prerequisites":"F\u00f6r tilltr\u00e4de till kursen kr\u00e4vs 75 avklarade h\u00f6gskolepo\u00e4ng fr\u00e5n ett ingenj\u00f6rsprogram inom maskinteknik eller industriell ekonomi inkluderande avklarad kurs H\u00e5llbarhetsgrunder, 6 hp.",
        "teacher":"ber",
        "teacher_url":"https:\/\/www.bth.se\/?searchtype=employee&s=ber",
        "replacement":null,
        "next_instance":"202436 (BRKHY)",
        "syllabus_url":"https:\/\/edu.bth.se\/utbildning\/redirect.asp?KtAnmKod=BRKHY&KtTermin=20242&lang=sv",
        "education_plan_url":"https:\/\/edu.bth.se\/utbildningsplaner\/IEACI_HT-22.pdf"
    },
    {
        "code":"IY1428",
        "name":"Ledarskap och organisation i kunskapsintensiva milj\u00f6er",
        "points":6.0,
        "semester":"H\u00f6sttermin 2024",
        "start_week":202445,
        "end_week":202503,
        "period":2,
        "type":"Obligatorisk",
        "focus":"Maskinteknik och h\u00e5llbar produktinnovation",
        "prerequisites":"F\u00f6r tilltr\u00e4de till kursen kr\u00e4vs avklarad kurs Teknisk introduktionskurs med ingenj\u00f6rsmetodik, 8 hp eller Grunder i spelutveckling, 8 hp.\n",
        "teacher":"jtr",
        "teacher_url":"https:\/\/www.bth.se\/?searchtype=employee&s=jtr",
        "replacement":null,
        "next_instance":"202445 (BHAEN)",
        "syllabus_url":"https:\/\/bth.azure-api.net\/lindplan\/courseplanbycode?code=BHAEN&semester=20242&lang=sv",
        "education_plan_url":"https:\/\/edu.bth.se\/utbildningsplaner\/IEACI_HT-22.pdf"
    },
    {
        "code":"IY1428",
        "name":"Ledarskap och organisation i kunskapsintensiva milj\u00f6er",
        "points":6.0,
        "semester":"H\u00f6sttermin 2024",
        "start_week":202445,
        "end_week":202503,
        "period":2,
        "type":"Obligatorisk",
        "focus":"Industriell mjukvaruutveckling",
        "prerequisites":"F\u00f6r tilltr\u00e4de till kursen kr\u00e4vs avklarad kurs Teknisk introduktionskurs med ingenj\u00f6rsmetodik, 8 hp eller Grunder i spelutveckling, 8 hp.\n",
        "teacher":"jtr",
        "teacher_url":"https:\/\/www.bth.se\/?searchtype=employee&s=jtr",
        "replacement":null,
        "next_instance":"202445 (BHAEN)",
        "syllabus_url":"https:\/\/bth.azure-api.net\/lindplan\/courseplanbycode?code=BHAEN&semester=20242&lang=sv",
        "education_plan_url":"https:\/\/edu.bth.se\/utbildningsplaner\/IEACI_HT-22.pdf"
    },
    {
        "code":"IY1420",
        "name":"Ekonometri",
        "points":6.0,
        "semester":"H\u00f6sttermin 2024",
        "start_week":202445,
        "end_week":202503,
        "period":2,
        "type":"Obligatorisk",
        "focus":"Maskinteknik och h\u00e5llbar produktinnovation",
        "prerequisites":"Grundl\u00e4ggande beh\u00f6righet samt genomg\u00e5ngna kurser i Mikroekonomi och strategi 6 hp samt F\u00f6retag och organisation 6 hp.\n",
        "teacher":"squ",
        "teacher_url":"https:\/\/www.bth.se\/?searchtype=employee&s=squ",
        "replacement":null,
        "next_instance":"202445 (BJPPG)",
        "syllabus_url":"https:\/\/bth.azure-api.net\/lindplan\/courseplanbycode?code=BJPPG&semester=20242&lang=sv",
        "education_plan_url":"https:\/\/edu.bth.se\/utbildningsplaner\/IEACI_HT-22.pdf"
    },
    {
        "code":"IY1420",
        "name":"Ekonometri",
        "points":6.0,
        "semester":"H\u00f6sttermin 2024",
        "start_week":202445,
        "end_week":202503,
        "period":2,
        "type":"Obligatorisk",
        "focus":"Industriell mjukvaruutveckling",
        "prerequisites":"Grundl\u00e4ggande beh\u00f6righet samt genomg\u00e5ngna kurser i Mikroekonomi och strategi 6 hp samt F\u00f6retag och organisation 6 hp.\n",
        "teacher":"squ",
        "teacher_url":"https:\/\/www.bth.se\/?searchtype=employee&s=squ",
        "replacement":null,
        "next_instance":"202445 (BJPPG)",
        "syllabus_url":"https:\/\/bth.azure-api.net\/lindplan\/courseplanbycode?code=BJPPG&semester=20242&lang=sv",
        "education_plan_url":"https:\/\/edu.bth.se\/utbildningsplaner\/IEACI_HT-22.pdf"
    },
    {
        "code":"PA2576",
        "name":"Programvaruintensiv produktutveckling",
        "points":12.0,
        "semester":"V\u00e5rtermin 2025",
        "start_week":202504,
        "end_week":202523,
        "period":3,
        "type":"Obligatorisk",
        "focus":"Industriell mjukvaruutveckling",
        "prerequisites":"F\u00f6r tilltr\u00e4de till kursen kr\u00e4vs avklarade kurser i programmering i en omfattning av 12 h\u00f6gskolepo\u00e4ng.",
        "teacher":"deb",
        "teacher_url":"https:\/\/www.bth.se\/?searchtype=employee&s=deb",
        "replacement":null,
        "next_instance":"202504 (BX6FJ)",
        "syllabus_url":"https:\/\/edu.bth.se\/utbildning\/redirect.asp?KtAnmKod=BX6FJ&KtTermin=20251&lang=sv",
        "education_plan_url":"https:\/\/edu.bth.se\/utbildningsplaner\/IEACI_HT-22.pdf"
    },
    {
        "code":"MT1540",
        "name":"Termodynamik",
        "points":6.0,
        "semester":"V\u00e5rtermin 2025",
        "start_week":202504,
        "end_week":202513,
        "period":3,
        "type":"Obligatorisk",
        "focus":"Maskinteknik och h\u00e5llbar produktinnovation",
        "prerequisites":"F\u00f6r tilltr\u00e4de till kursen kr\u00e4vs avklarade kurser Dynamik 6 hp eller Fysik f\u00f6r Ingenj\u00f6rer 2, 6 hp och Analys 2 6 hp samt genomg\u00e5ngna kurser Matematisk statistik, 6 hp och Fysik forts\u00e4ttningskurs, 6 hp eller Fysik f\u00f6r ingenj\u00f6rer 3, 6 hp.",
        "teacher":"che",
        "teacher_url":"https:\/\/www.bth.se\/?searchtype=employee&s=che",
        "replacement":"MT1574",
        "next_instance":"202614 (BP4TX)",
        "syllabus_url":"https:\/\/edu.bth.se\/utbildning\/redirect.asp?KtAnmKod=BAYAG&KtTermin=20251&lang=sv",
        "education_plan_url":"https:\/\/edu.bth.se\/utbildningsplaner\/IEACI_HT-22.pdf"
    },
    {
        "code":"MT1544",
        "name":"Materiall\u00e4ra",
        "points":6.0,
        "semester":"V\u00e5rtermin 2025",
        "start_week":202504,
        "end_week":202513,
        "period":3,
        "type":"Obligatorisk",
        "focus":"Maskinteknik och h\u00e5llbar produktinnovation",
        "prerequisites":"F\u00f6r tilltr\u00e4de till kursen ska 3 hp fr\u00e5n kursen H\u00e5llfasthetsl\u00e4ra grundkurs vara avklarad.",
        "teacher":"gkn",
        "teacher_url":"https:\/\/www.bth.se\/?searchtype=employee&s=gkn",
        "replacement":null,
        "next_instance":"202504 (BJ377)",
        "syllabus_url":"https:\/\/edu.bth.se\/utbildning\/redirect.asp?KtAnmKod=BJ377&KtTermin=20251&lang=sv",
        "education_plan_url":"https:\/\/edu.bth.se\/utbildningsplaner\/IEACI_HT-22.pdf"
    },
    {
        "code":"PA1472",
        "name":"Objektorienterad design",
        "points":6.0,
        "semester":"V\u00e5rtermin 2025",
        "start_week":202504,
        "end_week":202513,
        "period":3,
        "type":"Obligatorisk",
        "focus":"Industriell mjukvaruutveckling",
        "prerequisites":"F\u00f6r tilltr\u00e4de till kursen kr\u00e4vs att den studerande har avklarat programmering motsvarande 6 h\u00f6gskolepo\u00e4ng.\n",
        "teacher":"msv",
        "teacher_url":"https:\/\/www.bth.se\/?searchtype=employee&s=msv",
        "replacement":null,
        "next_instance":"202504 (BDQPQ)",
        "syllabus_url":"https:\/\/bth.azure-api.net\/lindplan\/courseplanbycode?code=BDQPQ&semester=20251&lang=sv",
        "education_plan_url":"https:\/\/edu.bth.se\/utbildningsplaner\/IEACI_HT-22.pdf"
    },
    {
        "code":"MT1568",
        "name":"Tillverkningsteknik",
        "points":6.0,
        "semester":"V\u00e5rtermin 2025",
        "start_week":202514,
        "end_week":202523,
        "period":4,
        "type":"Obligatorisk",
        "focus":"Maskinteknik och h\u00e5llbar produktinnovation",
        "prerequisites":"F\u00f6r tilltr\u00e4de till kursen kr\u00e4vs genomg\u00e5ngen teknisk introduktionskurs.\n",
        "teacher":"mmg",
        "teacher_url":"https:\/\/www.bth.se\/?searchtype=employee&s=mmg",
        "replacement":null,
        "next_instance":"202514 (B39P4)",
        "syllabus_url":"https:\/\/bth.azure-api.net\/lindplan\/courseplanbycode?code=B39P4&semester=20251&lang=sv",
        "education_plan_url":"https:\/\/edu.bth.se\/utbildningsplaner\/IEACI_HT-22.pdf"
    },
    {
        "code":"DV1682",
        "name":"Datastrukturer och algoritmer",
        "points":6.0,
        "semester":"V\u00e5rtermin 2025",
        "start_week":202514,
        "end_week":202523,
        "period":4,
        "type":"Obligatorisk",
        "focus":"Industriell mjukvaruutveckling",
        "prerequisites":"F\u00f6r tilltr\u00e4de till kursen kr\u00e4vs genomg\u00e5ngna kurser i grundl\u00e4ggande programmering motsvarande 5 hp samt objektorienterad programmering, 5 hp.\n",
        "teacher":"cno",
        "teacher_url":"https:\/\/www.bth.se\/?searchtype=employee&s=cno",
        "replacement":null,
        "next_instance":"202445 (BHJP4)",
        "syllabus_url":"https:\/\/bth.azure-api.net\/lindplan\/courseplanbycode?code=B7YUN&semester=20251&lang=sv",
        "education_plan_url":"https:\/\/edu.bth.se\/utbildningsplaner\/IEACI_HT-22.pdf"
    },
    {
        "code":"SL2542",
        "name":"H\u00e5llbara energisystem - grundkurs",
        "points":6.0,
        "semester":"V\u00e5rtermin 2025",
        "start_week":202514,
        "end_week":202523,
        "period":4,
        "type":"Obligatorisk",
        "focus":"Maskinteknik och h\u00e5llbar produktinnovation",
        "prerequisites":"F\u00f6r tilltr\u00e4de till kursen kr\u00e4vs avklarad kurs H\u00e5llbarhetsgrunder, 6 hp samt genomg\u00e5ngna kurser Termodynamik, 6 hp och Materiall\u00e4ra, 6 hp.",
        "teacher":"sbn",
        "teacher_url":"https:\/\/www.bth.se\/?searchtype=employee&s=sbn",
        "replacement":null,
        "next_instance":"202514 (B3N9M)",
        "syllabus_url":"https:\/\/edu.bth.se\/utbildning\/redirect.asp?KtAnmKod=B3N9M&KtTermin=20251&lang=sv",
        "education_plan_url":"https:\/\/edu.bth.se\/utbildningsplaner\/IEACI_HT-22.pdf"
    },
    {
        "code":"IY1422",
        "name":"Finansiell ekonomi",
        "points":6.0,
        "semester":"V\u00e5rtermin 2025",
        "start_week":202514,
        "end_week":202523,
        "period":4,
        "type":"Obligatorisk",
        "focus":"Maskinteknik och h\u00e5llbar produktinnovation",
        "prerequisites":"Grundl\u00e4ggande beh\u00f6righet samt genomg\u00e5ngna kurser i Grunderna i industriell ekonomi 6 hp, Mikroekonomi och strategi 6 hp och Ekonometri 6 hp.\n",
        "teacher":"aun",
        "teacher_url":"https:\/\/www.bth.se\/?searchtype=employee&s=aun",
        "replacement":null,
        "next_instance":"202514 (BF4JY)",
        "syllabus_url":"https:\/\/bth.azure-api.net\/lindplan\/courseplanbycode?code=BF4JY&semester=20251&lang=sv",
        "education_plan_url":"https:\/\/edu.bth.se\/utbildningsplaner\/IEACI_HT-22.pdf"
    },
    {
        "code":"IY1422",
        "name":"Finansiell ekonomi",
        "points":6.0,
        "semester":"V\u00e5rtermin 2025",
        "start_week":202514,
        "end_week":202523,
        "period":4,
        "type":"Obligatorisk",
        "focus":"Industriell mjukvaruutveckling",
        "prerequisites":"Grundl\u00e4ggande beh\u00f6righet samt genomg\u00e5ngna kurser i Grunderna i industriell ekonomi 6 hp, Mikroekonomi och strategi 6 hp och Ekonometri 6 hp.\n",
        "teacher":"aun",
        "teacher_url":"https:\/\/www.bth.se\/?searchtype=employee&s=aun",
        "replacement":null,
        "next_instance":"202514 (BF4JY)",
        "syllabus_url":"https:\/\/bth.azure-api.net\/lindplan\/courseplanbycode?code=BF4JY&semester=20251&lang=sv",
        "education_plan_url":"https:\/\/edu.bth.se\/utbildningsplaner\/IEACI_HT-22.pdf"
    },
    {
        "code":"IY2595",
        "name":"Produktionsekonomi",
        "points":7.0,
        "semester":"H\u00f6sttermin 2025",
        "start_week":202536,
        "end_week":202544,
        "period":1,
        "type":"Obligatorisk",
        "focus":"Maskinteknik och h\u00e5llbar produktinnovation",
        "prerequisites":"Avklarade kurser Introduktion till industriell ekonomi 6 hp, Mikroekonomi och strategi 6 hp eller motsvarande",
        "teacher":"hsa",
        "teacher_url":"https:\/\/www.bth.se\/?searchtype=employee&s=hsa",
        "replacement":null,
        "next_instance":"202436 (BUQMF)",
        "syllabus_url":"https:\/\/edu.bth.se\/utbildning\/redirect.asp?KtAnmKod=BEDWG&KtTermin=20252&lang=sv",
        "education_plan_url":"https:\/\/edu.bth.se\/utbildningsplaner\/IEACI_HT-22.pdf"
    },
    {
        "code":"IY2595",
        "name":"Produktionsekonomi",
        "points":7.0,
        "semester":"H\u00f6sttermin 2025",
        "start_week":202536,
        "end_week":202544,
        "period":1,
        "type":"Obligatorisk",
        "focus":"Industriell mjukvaruutveckling",
        "prerequisites":"Avklarade kurser Introduktion till industriell ekonomi 6 hp, Mikroekonomi och strategi 6 hp eller motsvarande",
        "teacher":"hsa",
        "teacher_url":"https:\/\/www.bth.se\/?searchtype=employee&s=hsa",
        "replacement":null,
        "next_instance":"202436 (BUQMF)",
        "syllabus_url":"https:\/\/edu.bth.se\/utbildning\/redirect.asp?KtAnmKod=BEDWG&KtTermin=20252&lang=sv",
        "education_plan_url":"https:\/\/edu.bth.se\/utbildningsplaner\/IEACI_HT-22.pdf"
    },
    {
        "code":"MT2569",
        "name":"Design Thinking",
        "points":7.0,
        "semester":"H\u00f6sttermin 2025",
        "start_week":202536,
        "end_week":202544,
        "period":1,
        "type":"Valbar",
        "focus":"Maskinteknik och h\u00e5llbar produktinnovation",
        "prerequisites":"F\u00f6r tilltr\u00e4de till kursen kr\u00e4vs 150 avklarade h\u00f6gskolepo\u00e4ng varav 60 hp fr\u00e5n ett cvilingenj\u00f6rsprogram i maskinteknik eller industriell ekonomi inkluderande avklarad kurs Produktutvecklingsmetodik (Innovativ- och h\u00e5llbar produktutveckling 1), 6 hp, Industriell ekonomi, \u00f6versiktskurs 6 hp eller Grunderna i industriell ekonomi 6 hp.",
        "teacher":"cmj",
        "teacher_url":"https:\/\/www.bth.se\/?searchtype=employee&s=cmj",
        "replacement":null,
        "next_instance":"202436 (E2656)",
        "syllabus_url":"https:\/\/edu.bth.se\/utbildning\/redirect.asp?KtAnmKod=BLGFJ&KtTermin=20252&lang=sv",
        "education_plan_url":"https:\/\/edu.bth.se\/utbildningsplaner\/IEACI_HT-22.pdf"
    },
    {
        "code":"MT2570",
        "name":"Knowledge Enabled Engineering",
        "points":7.0,
        "semester":"H\u00f6sttermin 2025",
        "start_week":202536,
        "end_week":202544,
        "period":1,
        "type":"Valbar",
        "focus":"Maskinteknik och h\u00e5llbar produktinnovation",
        "prerequisites":"F\u00f6r tilltr\u00e4de till kursen kr\u00e4vs 150 avklarade h\u00f6gskolepo\u00e4ng varav 60 hp ska vara fr\u00e5n ett civilingenj\u00f6rsprogram i maskinteknik eller industriell ekonomi. I de 60 hp ska kurs om minst 6 hp Datorst\u00f6dd konstruktion, CAD ( Datorst\u00f6d f\u00f6r Ingenj\u00f6rsarbete) ing\u00e5. Dessutom kr\u00e4vs genomg\u00e5ngen kurs om minst 6 hp i Produktutvecklingsmetodik (Innovativ och H\u00e5llbar produktutveckling 1) och Matematisk statistik 6 hp.",
        "teacher":"ber",
        "teacher_url":"https:\/\/www.bth.se\/?searchtype=employee&s=ber",
        "replacement":null,
        "next_instance":"202436 (BTPT9)",
        "syllabus_url":"https:\/\/edu.bth.se\/utbildning\/redirect.asp?KtAnmKod=BEC9M&KtTermin=20252&lang=sv",
        "education_plan_url":"https:\/\/edu.bth.se\/utbildningsplaner\/IEACI_HT-22.pdf"
    },
    {
        "code":"DV2618",
        "name":"Till\u00e4mpad artificiell intelligens",
        "points":7.0,
        "semester":"H\u00f6sttermin 2025",
        "start_week":202536,
        "end_week":202544,
        "period":1,
        "type":"Valbar",
        "focus":"Industriell mjukvaruutveckling",
        "prerequisites":"F\u00f6r tilltr\u00e4de till kursen kr\u00e4vs 12 avklarade hp fr\u00e5n moment i programmeringskurser (Python eller dylikt) samt 6 avklarade hp i datastrukturer och algoritmer.",
        "teacher":"hku",
        "teacher_url":"https:\/\/www.bth.se\/?searchtype=employee&s=hku",
        "replacement":null,
        "next_instance":"202436 (E2670)",
        "syllabus_url":"https:\/\/edu.bth.se\/utbildning\/redirect.asp?KtAnmKod=BQLUF&KtTermin=20252&lang=sv",
        "education_plan_url":"https:\/\/edu.bth.se\/utbildningsplaner\/IEACI_HT-22.pdf"
    },
    {
        "code":"DV1466",
        "name":"UNIX och Linux, en \u00f6versikt och introduktion",
        "points":7.0,
        "semester":"H\u00f6sttermin 2025",
        "start_week":202536,
        "end_week":202544,
        "period":1,
        "type":"Valbar",
        "focus":"Industriell mjukvaruutveckling",
        "prerequisites":"Grundl\u00e4ggande beh\u00f6righet.",
        "teacher":"dna",
        "teacher_url":"https:\/\/www.bth.se\/?searchtype=employee&s=dna",
        "replacement":null,
        "next_instance":"202436 (E2630)",
        "syllabus_url":"https:\/\/edu.bth.se\/utbildning\/redirect.asp?KtAnmKod=B39YK&KtTermin=20252&lang=sv",
        "education_plan_url":"https:\/\/edu.bth.se\/utbildningsplaner\/IEACI_HT-22.pdf"
    },
    {
        "code":"IY2583",
        "name":"F\u00f6retagsanalys",
        "points":7.0,
        "semester":"H\u00f6sttermin 2025",
        "start_week":202545,
        "end_week":202603,
        "period":2,
        "type":"Obligatorisk",
        "focus":"Maskinteknik och h\u00e5llbar produktinnovation",
        "prerequisites":"Avklarade kurser i Grunderna i industriell ekonomi 6 hp, Mikroekonomi och strategi 6 hp och Finansiell ekonomi 6 hp.",
        "teacher":"mit",
        "teacher_url":"https:\/\/www.bth.se\/?searchtype=employee&s=mit",
        "replacement":null,
        "next_instance":"202445 (BNRYW)",
        "syllabus_url":"https:\/\/edu.bth.se\/utbildning\/redirect.asp?KtAnmKod=BMKRW&KtTermin=20252&lang=sv",
        "education_plan_url":"https:\/\/edu.bth.se\/utbildningsplaner\/IEACI_HT-22.pdf"
    },
    {
        "code":"IY2583",
        "name":"F\u00f6retagsanalys",
        "points":7.0,
        "semester":"H\u00f6sttermin 2025",
        "start_week":202545,
        "end_week":202603,
        "period":2,
        "type":"Obligatorisk",
        "focus":"Industriell mjukvaruutveckling",
        "prerequisites":"Avklarade kurser i Grunderna i industriell ekonomi 6 hp, Mikroekonomi och strategi 6 hp och Finansiell ekonomi 6 hp.",
        "teacher":"mit",
        "teacher_url":"https:\/\/www.bth.se\/?searchtype=employee&s=mit",
        "replacement":null,
        "next_instance":"202445 (BNRYW)",
        "syllabus_url":"https:\/\/edu.bth.se\/utbildning\/redirect.asp?KtAnmKod=BMKRW&KtTermin=20252&lang=sv",
        "education_plan_url":"https:\/\/edu.bth.se\/utbildningsplaner\/IEACI_HT-22.pdf"
    },
    {
        "code":"SL2561",
        "name":"Strategisk planering f\u00f6r organisatoriska h\u00e5llbarhetsomst\u00e4llningar",
        "points":7.0,
        "semester":"H\u00f6sttermin 2025",
        "start_week":202545,
        "end_week":202603,
        "period":2,
        "type":"Valbar",
        "focus":"Maskinteknik och h\u00e5llbar produktinnovation",
        "prerequisites":"F\u00f6r tilltr\u00e4de till kursen kr\u00e4vs minst 120 avklarade hp samt genomg\u00e5ngen kurs omfattande minst 6 hp inom strategisk h\u00e5llbar utveckling inkluderande minst 2,5 hp om ramverket f\u00f6r strategisk h\u00e5llbar utveckling (FSSD). Engelska 6.",
        "teacher":"lwo",
        "teacher_url":"https:\/\/www.bth.se\/?searchtype=employee&s=lwo",
        "replacement":null,
        "next_instance":"202445 (E2675)",
        "syllabus_url":"https:\/\/edu.bth.se\/utbildning\/redirect.asp?KtAnmKod=B74RU&KtTermin=20252&lang=sv",
        "education_plan_url":"https:\/\/edu.bth.se\/utbildningsplaner\/IEACI_HT-22.pdf"
    },
    {
        "code":"DV2626",
        "name":"Maskininl\u00e4rning",
        "points":7.0,
        "semester":"H\u00f6sttermin 2025",
        "start_week":202545,
        "end_week":202603,
        "period":2,
        "type":"Valbar",
        "focus":"Industriell mjukvaruutveckling",
        "prerequisites":"F\u00f6r tilltr\u00e4de till kursen kr\u00e4vs en avklarad kurs i algoritmer och datastrukturer omfattande minst 6 hp och genomg\u00e5ngen kurs i till\u00e4mpad artificiell intelligens omfattande minst 6 hp.",
        "teacher":"vbx",
        "teacher_url":"https:\/\/www.bth.se\/?searchtype=employee&s=vbx",
        "replacement":null,
        "next_instance":"202445 (B7UDJ)",
        "syllabus_url":"https:\/\/edu.bth.se\/utbildning\/redirect.asp?KtAnmKod=B93C7&KtTermin=20252&lang=sv",
        "education_plan_url":"https:\/\/edu.bth.se\/utbildningsplaner\/IEACI_HT-22.pdf"
    },
    {
        "code":"MT2568",
        "name":"V\u00e4rdeinnovation",
        "points":7.0,
        "semester":"H\u00f6sttermin 2025",
        "start_week":202545,
        "end_week":202603,
        "period":2,
        "type":"Valbar",
        "focus":"Maskinteknik och h\u00e5llbar produktinnovation",
        "prerequisites":"F\u00f6r tilltr\u00e4de till kursen kr\u00e4vs 150 avklarade hp varav 60 hp fr\u00e5n ett civilingenj\u00f6rsprogram i maskinteknik eller industriell ekonomi. I de 60 hp ska kurserna Analys 1, 6 hp, kurs om minst 6hp i Produktutvecklingsmetodik (Innovativ och H\u00e5llbar produktutveckling 1) och grundkurs om minst 6 hp i Industriell ekonomi (Grunderna i industriell ekonomi, 6 hp \/ Industriell ekonomi, \u00f6versiktskurs, 6 hp) ing\u00e5. Dessutom kr\u00e4vs genomg\u00e5ngen kurs i H\u00e5llbarhetsgrunder, 6 hp och Matematisk statistik, 6 hp.",
        "teacher":"ber",
        "teacher_url":"https:\/\/www.bth.se\/?searchtype=employee&s=ber",
        "replacement":null,
        "next_instance":"202445 (E2657)",
        "syllabus_url":"https:\/\/edu.bth.se\/utbildning\/redirect.asp?KtAnmKod=BCX4M&KtTermin=20252&lang=sv",
        "education_plan_url":"https:\/\/edu.bth.se\/utbildningsplaner\/IEACI_HT-22.pdf"
    },
    {
        "code":"SL2543",
        "name":"H\u00e5llbar produktutveckling",
        "points":7.0,
        "semester":"H\u00f6sttermin 2025",
        "start_week":202545,
        "end_week":202603,
        "period":2,
        "type":"Valbar",
        "focus":"Maskinteknik och h\u00e5llbar produktinnovation",
        "prerequisites":"F\u00f6r tilltr\u00e4de till kursen kr\u00e4vs avklarad grundl\u00e4ggande kurs i h\u00e5llbarhet om minst 6 hp, exempelvis kursen H\u00e5llbarhetsgrunder, avklarat 2 hp i grundl\u00e4ggande produktutveckling och avklarat 1 hp i h\u00e5llbarhetsanalys inom produktutveckling, exempelvis fr\u00e5n kursen Innovativ- och h\u00e5llbar produktutveckling.",
        "teacher":"dcv",
        "teacher_url":"https:\/\/www.bth.se\/?searchtype=employee&s=dcv",
        "replacement":"SL2569",
        "next_instance":null,
        "syllabus_url":"https:\/\/edu.bth.se\/utbildning\/redirect.asp?KtAnmKod=B6Q3U&KtTermin=20252&lang=sv",
        "education_plan_url":"https:\/\/edu.bth.se\/utbildningsplaner\/IEACI_HT-22.pdf"
    },
    {
        "code":"MA2512",
        "name":"Till\u00e4mpad optimering",
        "points":7.0,
        "semester":"H\u00f6sttermin 2025",
        "start_week":202545,
        "end_week":202603,
        "period":2,
        "type":"Valbar",
        "focus":"Maskinteknik och h\u00e5llbar produktinnovation",
        "prerequisites":"Genomg\u00e5ngna kurser i Analys 12 hp, Flervariabelanalys 6 hp samt Linj\u00e4r algebra 6 hp.\n",
        "teacher":"yiv",
        "teacher_url":"https:\/\/www.bth.se\/?searchtype=employee&s=yiv",
        "replacement":null,
        "next_instance":"202445 (G5959)",
        "syllabus_url":"https:\/\/bth.azure-api.net\/lindplan\/courseplanbycode?code=B3Q3Q&semester=20252&lang=sv",
        "education_plan_url":"https:\/\/edu.bth.se\/utbildningsplaner\/IEACI_HT-22.pdf"
    },
    {
        "code":"MA2512",
        "name":"Till\u00e4mpad optimering",
        "points":7.0,
        "semester":"H\u00f6sttermin 2025",
        "start_week":202545,
        "end_week":202603,
        "period":2,
        "type":"Valbar",
        "focus":"Industriell mjukvaruutveckling",
        "prerequisites":"Genomg\u00e5ngna kurser i Analys 12 hp, Flervariabelanalys 6 hp samt Linj\u00e4r algebra 6 hp.\n",
        "teacher":"yiv",
        "teacher_url":"https:\/\/www.bth.se\/?searchtype=employee&s=yiv",
        "replacement":null,
        "next_instance":"202445 (G5959)",
        "syllabus_url":"https:\/\/bth.azure-api.net\/lindplan\/courseplanbycode?code=B3Q3Q&semester=20252&lang=sv",
        "education_plan_url":"https:\/\/edu.bth.se\/utbildningsplaner\/IEACI_HT-22.pdf"
    },
    {
        "code":"IY2606",
        "name":"Finansiell modellering",
        "points":7.0,
        "semester":"V\u00e5rtermin 2026",
        "start_week":202604,
        "end_week":202613,
        "period":3,
        "type":"Obligatorisk",
        "focus":"Maskinteknik och h\u00e5llbar produktinnovation",
        "prerequisites":"F\u00f6r tilltr\u00e4de till kursen kr\u00e4vs avklarad kurs Finansiell ekonomi, 6 hp.",
        "teacher":"squ",
        "teacher_url":"https:\/\/www.bth.se\/?searchtype=employee&s=squ",
        "replacement":null,
        "next_instance":"202504 (BDNEW)",
        "syllabus_url":"https:\/\/edu.bth.se\/utbildning\/redirect.asp?KtAnmKod=BQMTN&KtTermin=20261&lang=sv",
        "education_plan_url":"https:\/\/edu.bth.se\/utbildningsplaner\/IEACI_HT-22.pdf"
    },
    {
        "code":"IY2606",
        "name":"Finansiell modellering",
        "points":7.0,
        "semester":"V\u00e5rtermin 2026",
        "start_week":202604,
        "end_week":202613,
        "period":3,
        "type":"Obligatorisk",
        "focus":"Industriell mjukvaruutveckling",
        "prerequisites":"F\u00f6r tilltr\u00e4de till kursen kr\u00e4vs avklarad kurs Finansiell ekonomi, 6 hp.",
        "teacher":"squ",
        "teacher_url":"https:\/\/www.bth.se\/?searchtype=employee&s=squ",
        "replacement":null,
        "next_instance":"202504 (BDNEW)",
        "syllabus_url":"https:\/\/edu.bth.se\/utbildning\/redirect.asp?KtAnmKod=BQMTN&KtTermin=20261&lang=sv",
        "education_plan_url":"https:\/\/edu.bth.se\/utbildningsplaner\/IEACI_HT-22.pdf"
    },
    {
        "code":"IY2585",
        "name":"Projektkurs i industriell ekonomi och projektledning",
        "points":7.0,
        "semester":"V\u00e5rtermin 2026",
        "start_week":202604,
        "end_week":202623,
        "period":3,
        "type":"Obligatorisk",
        "focus":"Maskinteknik och h\u00e5llbar produktinnovation",
        "prerequisites":"Genomg\u00e5ngna 48 hp i industriell ekonomi och management.",
        "teacher":"mts",
        "teacher_url":"https:\/\/www.bth.se\/?searchtype=employee&s=mts",
        "replacement":null,
        "next_instance":"202504 (BMEJU)",
        "syllabus_url":"https:\/\/edu.bth.se\/utbildning\/redirect.asp?KtAnmKod=B7XGN&KtTermin=20261&lang=sv",
        "education_plan_url":"https:\/\/edu.bth.se\/utbildningsplaner\/IEACI_HT-22.pdf"
    },
    {
        "code":"IY2585",
        "name":"Projektkurs i industriell ekonomi och projektledning",
        "points":7.0,
        "semester":"V\u00e5rtermin 2026",
        "start_week":202604,
        "end_week":202623,
        "period":3,
        "type":"Obligatorisk",
        "focus":"Industriell mjukvaruutveckling",
        "prerequisites":"Genomg\u00e5ngna 48 hp i industriell ekonomi och management.",
        "teacher":"mts",
        "teacher_url":"https:\/\/www.bth.se\/?searchtype=employee&s=mts",
        "replacement":null,
        "next_instance":"202504 (BMEJU)",
        "syllabus_url":"https:\/\/edu.bth.se\/utbildning\/redirect.asp?KtAnmKod=B7XGN&KtTermin=20261&lang=sv",
        "education_plan_url":"https:\/\/edu.bth.se\/utbildningsplaner\/IEACI_HT-22.pdf"
    },
    {
        "code":"PA2539",
        "name":"Programvaruprojekt i team",
        "points":15.0,
        "semester":"V\u00e5rtermin 2026",
        "start_week":202604,
        "end_week":202623,
        "period":3,
        "type":"Obligatorisk",
        "focus":"Industriell mjukvaruutveckling",
        "prerequisites":"Genomg\u00e5tt kursen Programvaruintensiv produktutveckling.",
        "teacher":"tfr",
        "teacher_url":"https:\/\/www.bth.se\/?searchtype=employee&s=tfr",
        "replacement":null,
        "next_instance":"202504 (BTEFJ)",
        "syllabus_url":"https:\/\/edu.bth.se\/utbildning\/redirect.asp?KtAnmKod=B7QWK&KtTermin=20261&lang=sv",
        "education_plan_url":"https:\/\/edu.bth.se\/utbildningsplaner\/IEACI_HT-22.pdf"
    },
    {
        "code":"IY2628",
        "name":"Strategi och aff\u00e4rsutveckling",
        "points":7.0,
        "semester":"V\u00e5rtermin 2026",
        "start_week":202604,
        "end_week":202623,
        "period":3,
        "type":"Obligatorisk",
        "focus":"Maskinteknik och h\u00e5llbar produktinnovation",
        "prerequisites":"F\u00f6r tilltr\u00e4de till kursen kr\u00e4vs avklarade kurser Till\u00e4mpad mikroekonomi och strategi, 6 hp, F\u00f6retag och organisation, 6 hp, Industriell marknadsf\u00f6ring- Teori och praktik, 6 hp och Finansiell ekonomi, 6 hp.",
        "teacher":"mts",
        "teacher_url":"https:\/\/www.bth.se\/?searchtype=employee&s=mts",
        "replacement":null,
        "next_instance":"202504 (BWKDX)",
        "syllabus_url":"https:\/\/edu.bth.se\/utbildning\/redirect.asp?KtAnmKod=BCA9N&KtTermin=20261&lang=sv",
        "education_plan_url":"https:\/\/edu.bth.se\/utbildningsplaner\/IEACI_HT-22.pdf"
    },
    {
        "code":"DV1557",
        "name":"Anv\u00e4ndbarhet och interaktionsdesign",
        "points":7.0,
        "semester":"V\u00e5rtermin 2026",
        "start_week":202604,
        "end_week":202613,
        "period":3,
        "type":"Valbar",
        "focus":"Industriell mjukvaruutveckling",
        "prerequisites":"7\\.5 hp avklarad kurs inom huvudomr\u00e5det datavetenskap\n",
        "teacher":"yhx",
        "teacher_url":"https:\/\/www.bth.se\/?searchtype=employee&s=yhx",
        "replacement":null,
        "next_instance":"202504 (B737W)",
        "syllabus_url":"https:\/\/bth.azure-api.net\/lindplan\/courseplanbycode?code=BRW6L&semester=20261&lang=sv",
        "education_plan_url":"https:\/\/edu.bth.se\/utbildningsplaner\/IEACI_HT-22.pdf"
    },
    {
        "code":"IY2607",
        "name":"Empirisk finansiell analys",
        "points":7.0,
        "semester":"V\u00e5rtermin 2026",
        "start_week":202614,
        "end_week":202623,
        "period":4,
        "type":"Valbar",
        "focus":"Maskinteknik och h\u00e5llbar produktinnovation",
        "prerequisites":"F\u00f6r tilltr\u00e4de till kursen kr\u00e4vs avklarad kurs Finansiell ekonomi, 6 hp.",
        "teacher":"squ",
        "teacher_url":"https:\/\/www.bth.se\/?searchtype=employee&s=squ",
        "replacement":null,
        "next_instance":"202514 (E2689)",
        "syllabus_url":"https:\/\/edu.bth.se\/utbildning\/redirect.asp?KtAnmKod=BYKNX&KtTermin=20261&lang=sv",
        "education_plan_url":"https:\/\/edu.bth.se\/utbildningsplaner\/IEACI_HT-22.pdf"
    },
    {
        "code":"IY2607",
        "name":"Empirisk finansiell analys",
        "points":7.0,
        "semester":"V\u00e5rtermin 2026",
        "start_week":202614,
        "end_week":202623,
        "period":4,
        "type":"Valbar",
        "focus":"Industriell mjukvaruutveckling",
        "prerequisites":"F\u00f6r tilltr\u00e4de till kursen kr\u00e4vs avklarad kurs Finansiell ekonomi, 6 hp.",
        "teacher":"squ",
        "teacher_url":"https:\/\/www.bth.se\/?searchtype=employee&s=squ",
        "replacement":null,
        "next_instance":"202514 (E2689)",
        "syllabus_url":"https:\/\/edu.bth.se\/utbildning\/redirect.asp?KtAnmKod=BYKNX&KtTermin=20261&lang=sv",
        "education_plan_url":"https:\/\/edu.bth.se\/utbildningsplaner\/IEACI_HT-22.pdf"
    },
    {
        "code":"MT2578",
        "name":"Virtuell prototypframst\u00e4llning",
        "points":7.0,
        "semester":"V\u00e5rtermin 2026",
        "start_week":202614,
        "end_week":202623,
        "period":4,
        "type":"Valbar",
        "focus":"Maskinteknik och h\u00e5llbar produktinnovation",
        "prerequisites":"F\u00f6r tilltr\u00e4de till kursen kr\u00e4vs 150 avklarade hp varav 60 hp fr\u00e5n ett civilingenj\u00f6rsprogram i maskinteknik (eller motsvarande). I de 60 hp ska kurserna i produktutvecklingsmetodik (Innovativ och H\u00e5llbar produktutveckling 1\/Design Thinking), minst 6 hp och Datorst\u00f6d f\u00f6r ingenj\u00f6rer (eller motsvarande), minst 5 hp ing\u00e5.",
        "teacher":"gws",
        "teacher_url":"https:\/\/www.bth.se\/?searchtype=employee&s=gws",
        "replacement":null,
        "next_instance":"202514 (BN33Y)",
        "syllabus_url":"https:\/\/edu.bth.se\/utbildning\/redirect.asp?KtAnmKod=BH69F&KtTermin=20261&lang=sv",
        "education_plan_url":"https:\/\/edu.bth.se\/utbildningsplaner\/IEACI_HT-22.pdf"
    },
    {
        "code":"IY2586",
        "name":"Ekonomisk analys av teknikskiften",
        "points":7.0,
        "semester":"H\u00f6sttermin 2026",
        "start_week":202636,
        "end_week":202644,
        "period":1,
        "type":"Obligatorisk",
        "focus":"Maskinteknik och h\u00e5llbar produktinnovation",
        "prerequisites":"Avklarade kurser i Mikroekonomi och strategi 6 hp, F\u00f6retag och organisation 6 hp och Industriell\nmarknadsf\u00f6ring- teori och praktik 6 hp.",
        "teacher":"pro",
        "teacher_url":"https:\/\/www.bth.se\/?searchtype=employee&s=pro",
        "replacement":"IY2655",
        "next_instance":null,
        "syllabus_url":"https:\/\/edu.bth.se\/utbildning\/redirect.asp?KtAnmKod=B44A4&KtTermin=20262&lang=sv",
        "education_plan_url":"https:\/\/edu.bth.se\/utbildningsplaner\/IEACI_HT-22.pdf"
    },
    {
        "code":"IY2586",
        "name":"Ekonomisk analys av teknikskiften",
        "points":7.0,
        "semester":"H\u00f6sttermin 2026",
        "start_week":202636,
        "end_week":202644,
        "period":1,
        "type":"Obligatorisk",
        "focus":"Industriell mjukvaruutveckling",
        "prerequisites":"Avklarade kurser i Mikroekonomi och strategi 6 hp, F\u00f6retag och organisation 6 hp och Industriell\nmarknadsf\u00f6ring- teori och praktik 6 hp.",
        "teacher":"pro",
        "teacher_url":"https:\/\/www.bth.se\/?searchtype=employee&s=pro",
        "replacement":"IY2655",
        "next_instance":null,
        "syllabus_url":"https:\/\/edu.bth.se\/utbildning\/redirect.asp?KtAnmKod=B44A4&KtTermin=20262&lang=sv",
        "education_plan_url":"https:\/\/edu.bth.se\/utbildningsplaner\/IEACI_HT-22.pdf"
    },
    {
        "code":"DV2618",
        "name":"Till\u00e4mpad artificiell intelligens",
        "points":7.0,
        "semester":"H\u00f6sttermin 2026",
        "start_week":202636,
        "end_week":202644,
        "period":1,
        "type":"Valbar",
        "focus":"Industriell mjukvaruutveckling",
        "prerequisites":"F\u00f6r tilltr\u00e4de till kursen kr\u00e4vs 12 avklarade hp fr\u00e5n moment i programmeringskurser (Python eller dylikt) samt 6 avklarade hp i datastrukturer och algoritmer.",
        "teacher":"hku",
        "teacher_url":"https:\/\/www.bth.se\/?searchtype=employee&s=hku",
        "replacement":null,
        "next_instance":"202436 (E2670)",
        "syllabus_url":"https:\/\/edu.bth.se\/utbildning\/redirect.asp?KtAnmKod=BNMLM&KtTermin=20262&lang=sv",
        "education_plan_url":"https:\/\/edu.bth.se\/utbildningsplaner\/IEACI_HT-22.pdf"
    },
    {
        "code":"IY2603",
        "name":"Industriell organisation",
        "points":7.0,
        "semester":"H\u00f6sttermin 2026",
        "start_week":202636,
        "end_week":202644,
        "period":1,
        "type":"Valbar",
        "focus":"Maskinteknik och h\u00e5llbar produktinnovation",
        "prerequisites":"F\u00f6r tilltr\u00e4de till kursen kr\u00e4vs avklarade kurser i Till\u00e4mpad mikroekonomi, 6 hp och Matematisk statistik, 6 hp, d\u00e4rut\u00f6ver genomg\u00e5ngna kurser om 12 hp i industriell ekonomi och management.",
        "teacher":"mbh",
        "teacher_url":"https:\/\/www.bth.se\/?searchtype=employee&s=mbh",
        "replacement":null,
        "next_instance":"202436 (E2635)",
        "syllabus_url":"https:\/\/edu.bth.se\/utbildning\/redirect.asp?KtAnmKod=BQPRL&KtTermin=20262&lang=sv",
        "education_plan_url":"https:\/\/edu.bth.se\/utbildningsplaner\/IEACI_HT-22.pdf"
    },
    {
        "code":"IY2603",
        "name":"Industriell organisation",
        "points":7.0,
        "semester":"H\u00f6sttermin 2026",
        "start_week":202636,
        "end_week":202644,
        "period":1,
        "type":"Valbar",
        "focus":"Industriell mjukvaruutveckling",
        "prerequisites":"F\u00f6r tilltr\u00e4de till kursen kr\u00e4vs avklarade kurser i Till\u00e4mpad mikroekonomi, 6 hp och Matematisk statistik, 6 hp, d\u00e4rut\u00f6ver genomg\u00e5ngna kurser om 12 hp i industriell ekonomi och management.",
        "teacher":"mbh",
        "teacher_url":"https:\/\/www.bth.se\/?searchtype=employee&s=mbh",
        "replacement":null,
        "next_instance":"202436 (E2635)",
        "syllabus_url":"https:\/\/edu.bth.se\/utbildning\/redirect.asp?KtAnmKod=BQPRL&KtTermin=20262&lang=sv",
        "education_plan_url":"https:\/\/edu.bth.se\/utbildningsplaner\/IEACI_HT-22.pdf"
    },
    {
        "code":"MT2573",
        "name":"Transformativ produkt- och tj\u00e4nstesystemsinnovation",
        "points":15.0,
        "semester":"H\u00f6sttermin 2026",
        "start_week":202636,
        "end_week":202702,
        "period":1,
        "type":"Valbar",
        "focus":"Maskinteknik och h\u00e5llbar produktinnovation",
        "prerequisites":"F\u00f6r tilltr\u00e4de till kursen kr\u00e4vs minst 180 avklarade hp varav 80 hp fr\u00e5n ett ingenj\u00f6rsprogram i Maskinteknik, Industriell Ekonomi eller motsvarande, inkluderande avklarad kurs i produktutvecklingsmetodik (Design Thinking 7,5 hp Systems Engineering 7,5 hp V\u00e4rdeinnovation 7,5 hp eller motsvarande).",
        "teacher":"cmj",
        "teacher_url":"https:\/\/www.bth.se\/?searchtype=employee&s=cmj",
        "replacement":null,
        "next_instance":"202436 (BUDAU)",
        "syllabus_url":"https:\/\/edu.bth.se\/utbildning\/redirect.asp?KtAnmKod=BLEJ4&KtTermin=20262&lang=sv",
        "education_plan_url":"https:\/\/edu.bth.se\/utbildningsplaner\/IEACI_HT-22.pdf"
    },
    {
        "code":"IY2654",
        "name":"Forskningsmetod och design",
        "points":7.0,
        "semester":"H\u00f6sttermin 2026",
        "start_week":202645,
        "end_week":202702,
        "period":2,
        "type":"Obligatorisk",
        "focus":"Maskinteknik och h\u00e5llbar produktinnovation",
        "prerequisites":"F\u00f6r tilltr\u00e4de till kursen kr\u00e4vs 60 avklarade hp i\u00a0industriell ekonomi och management.\n",
        "teacher":"jbf",
        "teacher_url":"https:\/\/www.bth.se\/?searchtype=employee&s=jbf",
        "replacement":null,
        "next_instance":"202445 (B93WL)",
        "syllabus_url":"https:\/\/bth.azure-api.net\/lindplan\/courseplanbycode?code=BNYNJ&semester=20262&lang=sv",
        "education_plan_url":"https:\/\/edu.bth.se\/utbildningsplaner\/IEACI_HT-22.pdf"
    },
    {
        "code":"IY2654",
        "name":"Forskningsmetod och design",
        "points":7.0,
        "semester":"H\u00f6sttermin 2026",
        "start_week":202645,
        "end_week":202702,
        "period":2,
        "type":"Obligatorisk",
        "focus":"Industriell mjukvaruutveckling",
        "prerequisites":"F\u00f6r tilltr\u00e4de till kursen kr\u00e4vs 60 avklarade hp i\u00a0industriell ekonomi och management.\n",
        "teacher":"jbf",
        "teacher_url":"https:\/\/www.bth.se\/?searchtype=employee&s=jbf",
        "replacement":null,
        "next_instance":"202445 (B93WL)",
        "syllabus_url":"https:\/\/bth.azure-api.net\/lindplan\/courseplanbycode?code=BNYNJ&semester=20262&lang=sv",
        "education_plan_url":"https:\/\/edu.bth.se\/utbildningsplaner\/IEACI_HT-22.pdf"
    },
    {
        "code":"PA2557",
        "name":"Kvalitetsstyrning",
        "points":7.0,
        "semester":"H\u00f6sttermin 2026",
        "start_week":202645,
        "end_week":202702,
        "period":2,
        "type":"Valbar",
        "focus":"Industriell mjukvaruutveckling",
        "prerequisites":"Avklarade kurser omfattande minst 120 hp varav minst 90 hp inom f\u00f6ljande omr\u00e5den: Programvaruteknik, Datavetenskap eller Datalogi. Dessutom kr\u00e4vs en avklarad kurs p\u00e5 minst 7.5 hp inom Grundl\u00e4ggande Programvaruteknik (Software Engineering) eller Programvaruutvecklingsprojekt i grupp.",
        "teacher":"cjh",
        "teacher_url":"https:\/\/www.bth.se\/?searchtype=employee&s=cjh",
        "replacement":null,
        "next_instance":"202445 (E2622)",
        "syllabus_url":"https:\/\/edu.bth.se\/utbildning\/redirect.asp?KtAnmKod=BRENF&KtTermin=20262&lang=sv",
        "education_plan_url":"https:\/\/edu.bth.se\/utbildningsplaner\/IEACI_HT-22.pdf"
    },
    {
        "code":"DV2626",
        "name":"Maskininl\u00e4rning",
        "points":7.0,
        "semester":"H\u00f6sttermin 2026",
        "start_week":202645,
        "end_week":202702,
        "period":2,
        "type":"Valbar",
        "focus":"Industriell mjukvaruutveckling",
        "prerequisites":"F\u00f6r tilltr\u00e4de till kursen kr\u00e4vs en avklarad kurs i algoritmer och datastrukturer omfattande minst 6 hp och genomg\u00e5ngen kurs i till\u00e4mpad artificiell intelligens omfattande minst 6 hp.",
        "teacher":"vbx",
        "teacher_url":"https:\/\/www.bth.se\/?searchtype=employee&s=vbx",
        "replacement":null,
        "next_instance":"202445 (B7UDJ)",
        "syllabus_url":"https:\/\/edu.bth.se\/utbildning\/redirect.asp?KtAnmKod=BQLMM&KtTermin=20262&lang=sv",
        "education_plan_url":"https:\/\/edu.bth.se\/utbildningsplaner\/IEACI_HT-22.pdf"
    },
    {
        "code":"IY2608",
        "name":"Till\u00e4mpad konkurrens- och marknadsanalys",
        "points":7.0,
        "semester":"H\u00f6sttermin 2026",
        "start_week":202645,
        "end_week":202702,
        "period":2,
        "type":"Valbar",
        "focus":"Industriell mjukvaruutveckling",
        "prerequisites":"F\u00f6r tilltr\u00e4de till kursen kr\u00e4vs avklarade kurser i Till\u00e4mpad mikroekonomi, 6 hp och Matematisk statistik, 6 hp, d\u00e4rut\u00f6ver genomg\u00e5ngna kurser om 12 hp i industriell ekonomi och management.\n",
        "teacher":"tas",
        "teacher_url":"https:\/\/www.bth.se\/?searchtype=employee&s=tas",
        "replacement":null,
        "next_instance":"202445 (E2633)",
        "syllabus_url":"https:\/\/bth.azure-api.net\/lindplan\/courseplanbycode?code=BJMPK&semester=20262&lang=sv",
        "education_plan_url":"https:\/\/edu.bth.se\/utbildningsplaner\/IEACI_HT-22.pdf"
    },
    {
        "code":"IY2608",
        "name":"Till\u00e4mpad konkurrens- och marknadsanalys",
        "points":7.0,
        "semester":"H\u00f6sttermin 2026",
        "start_week":202645,
        "end_week":202702,
        "period":2,
        "type":"Valbar",
        "focus":"Maskinteknik och h\u00e5llbar produktinnovation",
        "prerequisites":"F\u00f6r tilltr\u00e4de till kursen kr\u00e4vs avklarade kurser i Till\u00e4mpad mikroekonomi, 6 hp och Matematisk statistik, 6 hp, d\u00e4rut\u00f6ver genomg\u00e5ngna kurser om 12 hp i industriell ekonomi och management.\n",
        "teacher":"tas",
        "teacher_url":"https:\/\/www.bth.se\/?searchtype=employee&s=tas",
        "replacement":null,
        "next_instance":"202445 (E2633)",
        "syllabus_url":"https:\/\/bth.azure-api.net\/lindplan\/courseplanbycode?code=BJMPK&semester=20262&lang=sv",
        "education_plan_url":"https:\/\/edu.bth.se\/utbildningsplaner\/IEACI_HT-22.pdf"
    },
    {
        "code":"DV1566",
        "name":"Introduktion till Cloud Computing",
        "points":7.0,
        "semester":"H\u00f6sttermin 2026",
        "start_week":202645,
        "end_week":202702,
        "period":2,
        "type":"Valbar",
        "focus":"Industriell mjukvaruutveckling",
        "prerequisites":"F\u00f6r tilltr\u00e4de till kursen kr\u00e4vs att den studerande har avklarat: programmering 15 hp, algoritmer och datastrukturer 6 hp  och  operativsystem 6 hp.",
        "teacher":"emc",
        "teacher_url":"https:\/\/www.bth.se\/?searchtype=employee&s=emc",
        "replacement":null,
        "next_instance":"202445 (E2626)",
        "syllabus_url":"https:\/\/edu.bth.se\/utbildning\/redirect.asp?KtAnmKod=B7X4R&KtTermin=20262&lang=sv",
        "education_plan_url":"https:\/\/edu.bth.se\/utbildningsplaner\/IEACI_HT-22.pdf"
    },
    {
        "code":"TE2502",
        "name":"Examensarbete f\u00f6r civilingenj\u00f6rer",
        "points":30.0,
        "semester":"V\u00e5rtermin 2027",
        "start_week":202703,
        "end_week":202722,
        "period":3,
        "type":"Obligatorisk",
        "focus":"Maskinteknik och h\u00e5llbar produktinnovation",
        "prerequisites":"F\u00f6r tilltr\u00e4de till kursen kr\u00e4vs att studenten har avklarat minst 240 hp som f\u00e5r ing\u00e5 i en civilingenj\u00f6rsexamen. Av dessa ska minst 30 hp vara avklarade kurser p\u00e5 avancerad niv\u00e5.",
        "teacher":"krw",
        "teacher_url":"https:\/\/www.bth.se\/?searchtype=employee&s=krw",
        "replacement":null,
        "next_instance":"202504 (BMMYN)",
        "syllabus_url":"https:\/\/edu.bth.se\/utbildning\/redirect.asp?KtAnmKod=BH4X7&KtTermin=20271&lang=sv",
        "education_plan_url":"https:\/\/edu.bth.se\/utbildningsplaner\/IEACI_HT-22.pdf"
    },
    {
        "code":"TE2502",
        "name":"Examensarbete f\u00f6r civilingenj\u00f6rer",
        "points":30.0,
        "semester":"V\u00e5rtermin 2027",
        "start_week":202703,
        "end_week":202722,
        "period":3,
        "type":"Obligatorisk",
        "focus":"Industriell mjukvaruutveckling",
        "prerequisites":"F\u00f6r tilltr\u00e4de till kursen kr\u00e4vs att studenten har avklarat minst 240 hp som f\u00e5r ing\u00e5 i en civilingenj\u00f6rsexamen. Av dessa ska minst 30 hp vara avklarade kurser p\u00e5 avancerad niv\u00e5.",
        "teacher":"krw",
        "teacher_url":"https:\/\/www.bth.se\/?searchtype=employee&s=krw",
        "replacement":null,
        "next_instance":"202504 (BMMYN)",
        "syllabus_url":"https:\/\/edu.bth.se\/utbildning\/redirect.asp?KtAnmKod=BH4X7&KtTermin=20271&lang=sv",
        "education_plan_url":"https:\/\/edu.bth.se\/utbildningsplaner\/IEACI_HT-22.pdf"
    }
]